mmdlp/__init__.py
mmdlp-0.0.1.dist-info/LICENSE
mmdlp-0.0.1.dist-info/METADATA
mmdlp-0.0.1.dist-info/WHEEL
mmdlp-0.0.1.dist-info/top_level.txt
mmdlp-0.0.1.dist-info/RECORD
